jsw_nx/__init__.py
jsw_nx/base/__init__.py
jsw_nx/base/every.py
jsw_nx/base/filter.py
jsw_nx/base/find.py
jsw_nx/base/find_index.py
jsw_nx/base/flatten.py
jsw_nx/base/foreach.py
jsw_nx/base/forin.py
jsw_nx/base/get.py
jsw_nx/base/getenv.py
jsw_nx/base/home.py
jsw_nx/base/includes.py
jsw_nx/base/index.py
jsw_nx/base/is_blank.py
jsw_nx/base/is_empty.py
jsw_nx/base/map.py
jsw_nx/base/mix.py
jsw_nx/base/noop.py
jsw_nx/base/parse_int.py
jsw_nx/base/reduce.py
jsw_nx/base/set.py
jsw_nx/base/some.py
jsw_nx/base/type.py
jsw_nx/classes/.gitkeep
jsw_nx/classes/__init__.py
jsw_nx/classes/baidu/fanyi.py
jsw_nx/classes/baidu/pan_share.py
jsw_nx/classes/baidu/pan_upload.py
jsw_nx/classes/baidu_fanyi.py
jsw_nx/classes/baidu_pan.py
jsw_nx/classes/configuration.py
jsw_nx/classes/date.py
jsw_nx/classes/fileutils.py
jsw_nx/classes/json.py
jsw_nx/classes/json_file.py
jsw_nx/classes/lc_option.py
jsw_nx/classes/pm2_manager.py
jsw_nx/classes/tar.py
jsw_nx/classes/weibo.py
jsw_nx/classes/yaml.py
jsw_nx/classes/ymd.py
jsw_nx/packages/.gitkeep
jsw_nx/packages/__init__.py
jsw_nx/packages/days.py
jsw_nx/packages/deep_each.py
jsw_nx/packages/env_select.py
jsw_nx/packages/filesize.py
jsw_nx/packages/get_domain.py
jsw_nx/packages/get_position.py
jsw_nx/packages/html2text.py
jsw_nx/packages/is_process_alive.py
jsw_nx/packages/md5.py
jsw_nx/packages/notify.py
jsw_nx/packages/param.py
jsw_nx/packages/parse_cookie.py
jsw_nx/packages/qs.py
jsw_nx/packages/random.py
jsw_nx/packages/random_ua.py
jsw_nx/packages/replace_dict_all.py
jsw_nx/packages/sample.py
jsw_nx/packages/sleep.py
jsw_nx/packages/sleep_random.py
jsw_nx/packages/tmpl.py
jsw_nx/packages/uniq.py
jsw_nx/packages/uniq_in_order.py
jsw_nx/packages/urljoin.py
jsw_nx/rubify/__init__.py
jsw_nx/rubify/times.py
jsw_nx/rubify/to_a.py
jsw_nx/rubify/to_b.py
jsw_nx/rubify/to_f.py
jsw_nx/rubify/to_i.py
jsw_nx/rubify/to_n.py
jsw_nx/rubify/to_s.py
jsw_nx/scrapy_utils/__init__.py
jsw_nx/scrapy_utils/url_ext.py
jsw_nx/scrapy_utils/url_ts.py
jsw_nx-1.0.158.dist-info/METADATA
jsw_nx-1.0.158.dist-info/WHEEL
jsw_nx-1.0.158.dist-info/RECORD
