Metadata-Version: 2.3
Name: jsw-nx
Version: 1.0.158
Summary: Next toolkit for python.
Home-page: https://js.work
Author: feizheng
Author-email: 1290657123@qq.com
Requires-Python: >=3.7,<4.0
Classifier: Programming Language :: Python :: 3
Classifier: Programming Language :: Python :: 3.7
Classifier: Programming Language :: Python :: 3.8
Classifier: Programming Language :: Python :: 3.9
Classifier: Programming Language :: Python :: 3.10
Classifier: Programming Language :: Python :: 3.11
Classifier: Programming Language :: Python :: 3.12
Classifier: Programming Language :: Python :: 3.13
Requires-Dist: bs4 (>=0.0.1,<0.0.2)
Requires-Dist: psutil (>=5.9.0,<6.0.0)
Requires-Dist: requests (>=2.28.1,<3.0.0)
Requires-Dist: ruamel.yaml (>=0.17.21,<0.18.0)
Project-URL: Repository, https://github.com/aric-pypi/jsw-nx
